typytemplate/__init__.py
typytemplate/main.py
typytemplate/templates/__init__.py
typytemplate/templates/dot_gitignore.py
typytemplate/templates/main_py.py
typytemplate/templates/makefile.py
typytemplate/templates/pyproject_toml.py
typytemplate/templates/readme_md.py
typytemplate/templates/test_main_py.py
typytemplate/templates/vscode_settings_json.py
typytemplate-0.1.3.dist-info/METADATA
typytemplate-0.1.3.dist-info/WHEEL
typytemplate-0.1.3.dist-info/entry_points.txt
typytemplate-0.1.3.dist-info/RECORD
