Metadata-Version: 2.1
Name: typytemplate
Version: 0.1.3
Summary: Lightweight Python project templating tool
License: Apache-2.0
Author: StephanMalan
Author-email: stephanmalan.rob@gmail.com
Requires-Python: >=3.11,<4.0
Classifier: License :: OSI Approved :: Apache Software License
Classifier: Programming Language :: Python :: 3
Classifier: Programming Language :: Python :: 3.11
